[
    {
        "message": "Fingerprint data",
        "ReceivedDate": "4/11/2023, 8:34:28 AM",
        "InstanceID": "FP_1",
        "EntityTypeID": "FP_1",
        "EntityTypeName": "Fingerprint",
        "ID": "FP_",
        "Code": "FPREG9500",
        "Operation": "Registered fingerprint",
        "DataSource": "FP_b0c65dad-b795-4e0b-96c1-d2ad1f7c44be"
    },
    {
        "message": "Fingerprint data",
        "ReceivedDate": "4/11/2023, 8:36:53 AM",
        "InstanceID": "FP_1",
        "EntityTypeID": "FP_1",
        "EntityTypeName": "Fingerprint",
        "ID": "FP_",
        "Code": "FPREG9500",
        "Operation": "Registered fingerprint",
        "DataSource": "FP_9f7734ca-27b0-44d8-b806-5d8163278c8a"
    },
    {
        "message": "Fingerprint data",
        "ReceivedDate": "4/11/2023, 8:37:59 AM",
        "InstanceID": "FP_2",
        "EntityTypeID": "FP_2",
        "EntityTypeName": "Fingerprint",
        "ID": "FP_",
        "Code": "FPREG9500",
        "Operation": "Registered fingerprint",
        "DataSource": "FP_3b832085-4b89-4d89-85ff-aff073b16a55"
    },
    {
        "message": "Fingerprint data",
        "ReceivedDate": "4/11/2023, 8:39:16 AM",
        "InstanceID": "FP_3",
        "EntityTypeID": "FP_3",
        "EntityTypeName": "Fingerprint",
        "ID": "FP_",
        "Code": "FPREG9500",
        "Operation": "Registered fingerprint",
        "DataSource": "FP_9ced0619-7668-42a1-a137-9fa29558673d"
    },
    {
        "message": "Fingerprint data",
        "ReceivedDate": "4/11/2023, 8:41:28 AM",
        "InstanceID": "FP_4",
        "EntityTypeID": "FP_4",
        "EntityTypeName": "Fingerprint",
        "ID": "FP_",
        "Code": "FPREG9500",
        "Operation": "Registered fingerprint",
        "DataSource": "FP_5cfd876c-a5fd-4150-bda7-9ea1b5a84368"
    },
    {
        "message": "Fingerprint data",
        "ReceivedDate": "4/11/2023, 8:41:52 AM",
        "InstanceID": "FP_5",
        "EntityTypeID": "FP_5",
        "EntityTypeName": "Fingerprint",
        "ID": "FP_",
        "Code": "FPREG9500",
        "Operation": "Registered fingerprint",
        "DataSource": "FP_c095594d-9157-4314-8154-265e58c4a9e9"
    },
    {
        "message": "Fingerprint data",
        "ReceivedDate": "4/11/2023, 8:45:26 AM",
        "InstanceID": "FP_6",
        "EntityTypeID": "FP_6",
        "EntityTypeName": "Fingerprint",
        "ID": "FP_",
        "Code": "FPREG9500",
        "Operation": "Registered fingerprint",
        "DataSource": "FP_a4f98219-08b9-414a-b951-8931716cb3dd"
    },
    {
        "message": "Fingerprint data",
        "ReceivedDate": "4/11/2023, 8:47:09 AM",
        "InstanceID": "FP_7",
        "EntityTypeID": "FP_7",
        "EntityTypeName": "Fingerprint",
        "ID": "FP_",
        "Code": "FPREG9500",
        "Operation": "Registered fingerprint",
        "DataSource": "FP_3bdb5d4c-1b4f-4476-be75-1dc638e2426a"
    },
    {
        "message": "Fingerprint data",
        "ReceivedDate": "4/11/2023, 8:47:55 AM",
        "InstanceID": "FP_8",
        "EntityTypeID": "FP_8",
        "EntityTypeName": "Fingerprint",
        "ID": "FP_",
        "Code": "FPREG9500",
        "Operation": "Registered fingerprint",
        "DataSource": "FP_519312b1-e312-4e08-a9b8-cfcb11732a48"
    }
]